onesharepy/__init__.py
onesharepy/__main__.py
onesharepy-0.0.4.dist-info/licenses/LICENSE
onesharepy-0.0.4.dist-info/METADATA
onesharepy-0.0.4.dist-info/WHEEL
onesharepy-0.0.4.dist-info/top_level.txt
onesharepy-0.0.4.dist-info/RECORD
