Metadata-Version: 2.4
Name: onesharepy
Version: 0.0.4
Summary: Download personal onedrive files.
Author: xiongzhen
License:                     GNU AFFERO GENERAL PUBLIC LICENSE
Project-URL: Homepage, https://github.com/xiongzhen/onesharepy
Keywords: onedrive
Classifier: Development Status :: 4 - Beta
Classifier: Intended Audience :: End Users/Desktop
Classifier: Topic :: Utilities
Classifier: License :: OSI Approved :: GNU Affero General Public License v3
Classifier: Programming Language :: Python :: 3.13
Requires-Python: >=3.13
License-File: LICENSE
Requires-Dist: aiohttp>=3.12
Requires-Dist: requests>=2.32
Provides-Extra: dev
Dynamic: license-file
